AreYouHuman/__init__.py
AreYouHuman/cli.py
AreYouHuman/exception/__init__.py
AreYouHuman/exception/captcha.py
AreYouHuman/types/__init__.py
AreYouHuman/types/callback.py
AreYouHuman/types/captcha.py
AreYouHuman/types/response.py
AreYouHuman/types/settings.py
AreYouHuman/utils/__init__.py
AreYouHuman/utils/keyboard.py
examples/settings.py
examples/telegram_bot/main.py
examples/telegram_bot/filters/__init__.py
examples/telegram_bot/filters/user_check.py
examples/telegram_bot/middlewares/__init__.py
examples/telegram_bot/middlewares/get_response.py
examples/telegram_bot/routers/__init__.py
examples/telegram_bot/routers/captcha_cant_click.py
examples/telegram_bot/routers/captcha_click.py
examples/telegram_bot/routers/captcha_confirm.py
examples/telegram_bot/routers/captcha_generate.py
areyouhumanlib-0.1.7.1.dist-info/METADATA
areyouhumanlib-0.1.7.1.dist-info/WHEEL
areyouhumanlib-0.1.7.1.dist-info/entry_points.txt
areyouhumanlib-0.1.7.1.dist-info/top_level.txt
areyouhumanlib-0.1.7.1.dist-info/RECORD
