Metadata-Version: 2.4
Name: AreYouHumanLib
Version: 0.1.7.1
Summary: .
Author-email: Andrzej <andrzej.krajnow1337@gmail.com>
License: MIT
Requires-Python: >=3.8
Requires-Dist: emoji_data_python>=1.6.0
Requires-Dist: alive-progress>=3.2.0
Requires-Dist: requests>=2.32.0
Requires-Dist: aiogram>=3.18.0
Requires-Dist: pillow>=11.2.1
Requires-Dist: click>=8.1.8
Requires-Dist: numpy>=2.2.4
